pytest_vcr_delete_on_fail/__init__.py
pytest_vcr_delete_on_fail/main.py
pytest_vcr_delete_on_fail-2.0.1.dist-info/LICENSE
pytest_vcr_delete_on_fail-2.0.1.dist-info/METADATA
pytest_vcr_delete_on_fail-2.0.1.dist-info/WHEEL
pytest_vcr_delete_on_fail-2.0.1.dist-info/entry_points.txt
pytest_vcr_delete_on_fail-2.0.1.dist-info/RECORD
