Metadata-Version: 2.1
Name: pytest-vcr-delete-on-fail
Version: 2.0.1
Summary: A pytest plugin that automates vcrpy cassettes deletion on test failure.
Home-page: https://github.com/CarloDePieri/pytest-vcr-delete-on-fail
License: GPL-3.0-only
Keywords: pytest,vcr,testing,vcrpy,fail,delete
Author: Carlo De Pieri
Author-email: depieri.carlo@gmail.com
Requires-Python: >=3.8.1,<4.0.0
Classifier: Development Status :: 5 - Production/Stable
Classifier: Environment :: Console
Classifier: Intended Audience :: Developers
Classifier: License :: OSI Approved :: GNU General Public License v3 (GPLv3)
Classifier: Programming Language :: Python :: 3
Classifier: Programming Language :: Python :: 3.9
Classifier: Programming Language :: Python :: 3.10
Classifier: Programming Language :: Python :: 3.11
Classifier: Programming Language :: Python :: 3.12
Classifier: Programming Language :: Python :: 3.8
Classifier: Topic :: Software Development :: Testing
Classifier: Topic :: Utilities
Requires-Dist: pytest (>=8.0.0,<9.0.0)
Project-URL: Documentation, https://carlodepieri.github.io/pytest-vcr-delete-on-fail
Project-URL: Repository, https://github.com/CarloDePieri/pytest-vcr-delete-on-fail
